{
  "members": [
    {
      "company": "Agrocentro S.A.",
      "address": "14 calle 3-01 zona 9",
      "phone": "(502)2381-2381",
      "website": "https://www.agrocentro.com",
      "logo": "https://luroblesf.github.io/wdd230/chamber/images/agrocentro.webp",
      "membership": "Silver"
    },
    {
      "name": "Disagro Guatemala S.A.",
      "address": "Anillo Periferico 17-36 zona 11",
      "phone": "(502) 2474-9300",
      "website": "https://www.disagro.com",
      "imageurl": "https://luroblesf.github.io/wdd230/chamber/images/disagro.webp",
      "membership": "Silver"
    }
  ]
}  